doraemon/__init__.py
doraemon/built/__init__.py
doraemon/built/attention_based_pooler.py
doraemon/built/class_augmenter.py
doraemon/built/layer_optimizer.py
doraemon/dataset/__init__.py
doraemon/dataset/basedataset.py
doraemon/dataset/dataprocessor.py
doraemon/dataset/transforms.py
doraemon/distills/__init__.py
doraemon/distills/distillers.py
doraemon/engine/__init__.py
doraemon/engine/optimizer.py
doraemon/engine/scheduler.py
doraemon/engine/vision_engine.py
doraemon/engine/procedure/__init__.py
doraemon/engine/procedure/eval_recog.py
doraemon/engine/procedure/train.py
doraemon/engine/procedure/visualizer.py
doraemon/engine/representation/__init__.py
doraemon/engine/representation/eval_cbir.py
doraemon/engine/representation/eval_face.py
doraemon/models/__init__.py
doraemon/models/ema.py
doraemon/models/smartmodel.py
doraemon/models/classifier/__init__.py
doraemon/models/classifier/classify_model.py
doraemon/models/losses/__init__.py
doraemon/models/losses/loss.py
doraemon/models/representation/__init__.py
doraemon/models/representation/face_model.py
doraemon/models/representation/backbone/__init__.py
doraemon/models/representation/backbone/backbone_def.py
doraemon/models/representation/backbone/timm_wrapper.py
doraemon/models/representation/head/__init__.py
doraemon/models/representation/head/arcface.py
doraemon/models/representation/head/circleloss.py
doraemon/models/representation/head/head_def.py
doraemon/models/representation/head/magface.py
doraemon/models/representation/head/mv_softmax.py
doraemon/structure/__init__.py
doraemon/structure/sampler.py
doraemon/utils/__init__.py
doraemon/utils/average_meter.py
doraemon/utils/cam.py
doraemon/utils/checks.py
doraemon/utils/logger.py
doraemon/utils/plots.py
doraemon_torch-0.0.1.dist-info/LICENSE
doraemon_torch-0.0.1.dist-info/METADATA
doraemon_torch-0.0.1.dist-info/WHEEL
doraemon_torch-0.0.1.dist-info/top_level.txt
doraemon_torch-0.0.1.dist-info/RECORD
