Metadata-Version: 2.2
Name: doraemon-torch
Version: 0.0.1
Summary: Doraemon
Home-page: https://github.com/wuji3/Doraemon
Author: duke
Author-email: dk812821001@163.com
Requires-Python: >=3.10
License-File: LICENSE
Requires-Dist: torchmetrics==0.11.4
Requires-Dist: opencv-python==4.7.0.72
Requires-Dist: numpy==1.24.3
Requires-Dist: tqdm==4.66.4
Requires-Dist: Pillow==9.4.0
Requires-Dist: grad-cam==1.4.8
Requires-Dist: timm==0.9.16
Requires-Dist: tensorboard==2.16.2
Requires-Dist: prettytable==3.10.0
Requires-Dist: datasets==2.20.0
Requires-Dist: imagehash==4.3.1
Requires-Dist: transformers==4.48.3
Requires-Dist: torch==2.5.1
Requires-Dist: faiss-cpu==1.7.2
Dynamic: author
Dynamic: author-email
Dynamic: description
Dynamic: description-content-type
Dynamic: home-page
Dynamic: requires-dist
Dynamic: requires-python
Dynamic: summary
